csv_to_dictionary/__init__.py
csv_to_dictionary/csv_to_dictionary.py
csv_to_dictionary-1.0.6.dist-info/DESCRIPTION.rst
csv_to_dictionary-1.0.6.dist-info/METADATA
csv_to_dictionary-1.0.6.dist-info/RECORD
csv_to_dictionary-1.0.6.dist-info/WHEEL
csv_to_dictionary-1.0.6.dist-info/metadata.json
csv_to_dictionary-1.0.6.dist-info/top_level.txt
