Metadata-Version: 1.1
Name: csv_to_dictionary
Version: 1.0.6
Summary: Ultra simple csv to dictionary conversion library
Home-page: https://github.com/EthanDayley/csv_to_dictionary
Author: Ethan Dayley
Author-email: UNKNOWN
License: UNKNOWN
Keywords: simple csv dictionary parser
Platform: UNKNOWN
Classifier: Development Status :: 3 - Alpha
Classifier: Intended Audience :: Developers
Classifier: License :: OSI Approved :: MIT License
Classifier: Programming Language :: Python :: 3
